{
  "symbols": [
    {
      "id": "drzwi-otwarte",
      "name": "Drzwi otwarte"
    },
    {
      "id": "drzwi-zamknięte",
      "name": "Drzwi zamknięte"
    },
    {
      "id": "życie",
      "name": "Znacznik zdrowia"
    },
    {
      "id": "rewers",
      "name": "Żeton ruchu"
    },
    {
      "id": "amunicja-pistolet",
      "name": "Amunicja do pistoletu"
    },
    {
      "id": "amunicja-strzelba",
      "name": "Amunicja do strzelby"
    },
    {
      "id": "losowe",
      "name": "Marker losowy"
    },
    {
      "id": "pd",
      "name": "Punkt doświadczenia"
    },
    {
      "id": "paragraf",
      "name": "Symbol paragrafu"
    }
  ]
}
